fff_profile_picture/__init__.py
fff_profile_picture/templates/FaceTheClimateEmergency.png
fff_profile_picture/templates/kgw.png
fff_profile_picture-2.1.5.dist-info/LICENSE
fff_profile_picture-2.1.5.dist-info/METADATA
fff_profile_picture-2.1.5.dist-info/WHEEL
fff_profile_picture-2.1.5.dist-info/top_level.txt
fff_profile_picture-2.1.5.dist-info/RECORD
